_pycryptonight.cpython-310-darwin.so
pycryptonight/__init__.py
pycryptonight/tests/__init__.py
pycryptonight/tests/test.py
pycryptonight/tests/data/tests-fast.txt
pycryptonight/tests/data/tests-slow-1.txt
pycryptonight/tests/data/tests-slow-2.txt
pycryptonight/tests/data/tests-slow-4.txt
pycryptonight/tests/data/tests-slow.txt
py_cryptonight-1.0.0.dist-info/LICENSE
py_cryptonight-1.0.0.dist-info/METADATA
py_cryptonight-1.0.0.dist-info/WHEEL
py_cryptonight-1.0.0.dist-info/top_level.txt
py_cryptonight-1.0.0.dist-info/RECORD
