Metadata-Version: 2.1
Name: py-cryptonight
Version: 1.0.0
Summary: Python Cryptonight
Home-page: https://github.com/ph4r05/py-cryptonight
Author: Dusan Klinec
Author-email: dusan.klinec@gmail.com
License: MIT
Classifier: Development Status :: 3 - Alpha
Classifier: Intended Audience :: Developers
Classifier: Programming Language :: Python
Classifier: Programming Language :: Python :: 2.7
Classifier: Programming Language :: Python :: 3.5
Classifier: Programming Language :: Python :: 3.6
Classifier: Topic :: Security
License-File: LICENSE
Provides-Extra: dev
Requires-Dist: nose ; extra == 'dev'
Requires-Dist: pep8 ; extra == 'dev'
Requires-Dist: tox ; extra == 'dev'
Requires-Dist: aiounittest ; extra == 'dev'
Provides-Extra: docs
Requires-Dist: Sphinx (>=1.0) ; extra == 'docs'
Requires-Dist: sphinx-rtd-theme ; extra == 'docs'
Requires-Dist: sphinxcontrib-programoutput ; extra == 'docs'
